pyxtension/Json.py
pyxtension/__init__.py
pyxtension/fileutils.py
pyxtension/models.py
pyxtension/racelib.py
pyxtension/streams.py
pyxtension/throttler.py
roys_pyxtension-1.0.2.data/data/requirements.txt
roys_pyxtension-1.0.2.dist-info/LICENSE
roys_pyxtension-1.0.2.dist-info/METADATA
roys_pyxtension-1.0.2.dist-info/WHEEL
roys_pyxtension-1.0.2.dist-info/top_level.txt
roys_pyxtension-1.0.2.dist-info/RECORD
