Metadata-Version: 2.1
Name: roys-pyxtension
Version: 1.0.2
Summary: Extension library for Python, forked from https://github.com/asuiu/pyxtension
Home-page: https://github.com/roymanigley/streamerate
Author: Roy Manigley
Author-email: roy.manigley@gmail.com
License: UNKNOWN
Platform: UNKNOWN
Classifier: Development Status :: 5 - Production/Stable
Classifier: Intended Audience :: Developers
Classifier: Programming Language :: Python :: 2.7
Classifier: Programming Language :: Python :: 3.6
Classifier: Programming Language :: Python :: 3.7
Classifier: Programming Language :: Python :: 3.8
Classifier: Programming Language :: Python :: Implementation :: CPython
Classifier: Programming Language :: Python :: Implementation :: PyPy
Requires-Python: >=3.6, <4
License-File: LICENSE
Requires-Dist: json-composite-encoder (>=1.0.0)
Requires-Dist: pydantic (>=1.8.2) ; python_version >= "3"
Requires-Dist: tblib (>=1.7.0) ; python_version >= "3"
Requires-Dist: tqdm (>=4.62.0) ; python_version >= "3"
Provides-Extra: dev
Requires-Dist: mock ; (python_version < "3") and extra == 'dev'
Provides-Extra: test
Requires-Dist: mock ; (python_version < "3") and extra == 'test'
